samplify/__init__.py
samplify/api_requestor.py
samplify/resources.py
samplify/version.py
samplify_python-0.0.9.13.dist-info/LICENSE
samplify_python-0.0.9.13.dist-info/METADATA
samplify_python-0.0.9.13.dist-info/WHEEL
samplify_python-0.0.9.13.dist-info/top_level.txt
samplify_python-0.0.9.13.dist-info/RECORD
