Metadata-Version: 2.1
Name: samplify-python
Version: 0.0.9.13
Summary: Python wrapper for Samplify API
Home-page: https://samplify.io
Author: Samplify Limited
Author-email: developers@samplify.io
License: MIT
Platform: UNKNOWN
Requires-Dist: requests
